pyoptgra/__init__.py
pyoptgra/_about.py
pyoptgra/khan.py
pyoptgra/optgra.py
pyoptgra/timeout.py
pyoptgra/core/__init__.py
pyoptgra/core/bindings.cpp
pyoptgra/core/core.cpython-312-x86_64-linux-gnu.so
pyoptgra/core/mul2m.F
pyoptgra/core/mulvs.F
pyoptgra/core/ogcdel.F
pyoptgra/core/ogclos.F
pyoptgra/core/ogcorr.F
pyoptgra/core/ogcpri.F
pyoptgra/core/ogcsca.F
pyoptgra/core/ogcstr.F
pyoptgra/core/ogctyp.F
pyoptgra/core/ogdata.inc
pyoptgra/core/ogderi.F
pyoptgra/core/ogdist.F
pyoptgra/core/ogeval.F
pyoptgra/core/ogexcl.F
pyoptgra/core/ogexec.F
pyoptgra/core/oggsst.F
pyoptgra/core/ogincl.F
pyoptgra/core/oginit.F
pyoptgra/core/ogiter.F
pyoptgra/core/ogleft.F
pyoptgra/core/ogomet.F
pyoptgra/core/ogopti.F
pyoptgra/core/ogplog.F
pyoptgra/core/ogpwri.F
pyoptgra/core/ogpwri_end.F
pyoptgra/core/ogpwri_start.F
pyoptgra/core/ogrigt.F
pyoptgra/core/ogsens.F
pyoptgra/core/ogsopt.F
pyoptgra/core/ogssst.F
pyoptgra/core/ogvsca.F
pyoptgra/core/ogvstr.F
pyoptgra/core/ogvtyp.F
pyoptgra/core/ogwlog.F
pyoptgra/core/ogwmat.F
pyoptgra/core/ogwrit.F
pyoptgra/core/ogwtab.F
pyoptgra/core/sum2v.F
pyoptgra/core/wrapper.hpp
pyoptgra/core/lib/liboptgra.a
pyoptgra.libs/libgfortran-040039e1.so.5.0.0
pyoptgra.libs/libquadmath-96973f99.so.0.0.0
pyoptgra-1.3.0.dist-info/METADATA
pyoptgra-1.3.0.dist-info/WHEEL
pyoptgra-1.3.0.dist-info/RECORD
pyoptgra-1.3.0.dist-info/sboms/auditwheel.cdx.json
