Metadata-Version: 2.2
Name: pyoptgra
Version: 1.3.0
Summary: A python-wrapped version of OPTGRA, an algorithm for constrained optimization
Author-Email: Johannes Schoenmaekers <johannes.schoenmaekers@esa.int>, Moritz von Looz <moritz.von.looz@esa.int>, Waldemar Martens <waldemar.martens@esa.int>
License: GPL-3.0 or ESCL-2.4
Requires-Python: >=3.9
Requires-Dist: pygmo>=2.16.0
Requires-Dist: numpy<2.0.0
